Workbook

Sheet Daily plan
A2: Sebastian's October 2026 re-entry plan
A4: DS = Data Science / Analytics. DE = Data Engineering. Job starts Monday, October 26.
A5: Each track: P1 = 25 minutes minimum; P2 = optional second 25-minute block. Use Progress to log either hands-on or concept work.
A6: Date | B6: Track | C6: Focus | D6: P1: minimum task | E6: P2: optional extension | F6: Concept-only alternative / search topic | G6: Hands-on checkpoint
A7: 46296 | B7: DS | C7: Establish a baseline | D7: Create a small messy maintenance CSV and profile shape, types, missingness, and duplicates in Jupyter. | E7: Write three questions the data could answer. | F7: Search pandas data profiling refresher; describe a first-pass inspection and three failure modes in a note. | G7: A baseline notebook and three findings.
A8: 46296 | B8: DE | C8: Establish a baseline | D8: Sketch CSV → staging → cleaned tables → queries; state what one input row represents. | E8: Create the folders above and a short field dictionary. | F8: Search ETL ELT staging data grain; narrate the stages, inputs, and outputs for this dataset. | G8: Pipeline sketch and explicit row grain.
A9: 46297 | B9: DS | C9: Clean types and identifiers | D9: Standardize whitespace, null markers, dates, and numeric columns while preserving raw values. | E9: Compare before/after null counts and inspect failed conversions. | F9: Search pandas missing values dtype date parsing; explain five cleaning rules and when each could destroy information. | G9: Cleaning rules and a conversion report.
A10: 46297 | B10: DE | C10: Clean types and identifiers | D10: Read the CSV with explicit encoding, delimiter, and identifier types; preserve leading zeros. | E10: Separate malformed rows with reasons. | F10: Search CSV ingestion encoding delimiters schema validation; draft an input contract with three rejection rules. | G10: Ingestion function and a small rejected-row sample.
A11: 46298 | B11: DS | C11: Duplicates, grain, and keys | D11: Distinguish duplicate rows from legitimate repeat maintenance events. | E11: Compare deduplication strategies and their effect on counts. | F11: Search data deduplication entity resolution basics; explain why matching asset IDs alone cannot identify duplicate events. | G11: A defensible duplicate rule with examples.
A12: 46298 | B12: DE | C12: Duplicates, grain, and keys | D12: Identify candidate, primary, natural, surrogate, and foreign keys for assets and work orders. | E12: Check candidate keys for nulls and uniqueness. | F12: Search candidate key natural key surrogate key foreign key; explain your choices for two related tables. | G12: Key choices and failed-key examples.
A13: 46299 | B13: DS | C13: First normal form | D13: Split and explode a multi-part field; compare row counts before and after. | E13: Aggregate back to work-order grain without double-counting costs. | F13: Search pandas explode double counting aggregation; work through one order with three parts and explain the counting trap. | G13: A notebook showing the grain change.
A14: 46299 | B14: DE | C14: First normal form | D14: Convert repeating part columns or lists into rows with single values in each field: a practical 1NF exercise. | E14: Define a work-order-parts table and its key. | F14: Search first normal form repeating groups atomic values; sketch a corrected table from a three-part order. | G14: Before/after tables and a 1NF explanation.
A15: 46300 | B15: DS | C15: Second normal form | D15: Refresh groupby, aggregation, and pivoting to compare work orders by unit. | E15: Check denominators and distinguish asset counts from order counts. | F15: Search aggregation grain numerator denominator analytics; calculate a metric from a small invented example. | G15: One summary with a written metric definition.
A16: 46300 | B16: DE | C16: Second normal form | D16: Use the composite key (work_order_id, part_id); move attributes dependent on only one key component into their own tables. | E16: Write the functional dependencies. | F16: Search second normal form partial dependency composite key; explain why part name belongs with the part, not the order-part pair. | G16: A 2NF schema and the partial dependency removed.
A17: 46301 | B17: DS | C17: Third normal form and relationships | D17: Join assets, units, and orders; validate expected one-to-many relationships. | E17: Find unmatched keys and accidental row multiplication. | F17: Search pandas merge validate SQL join cardinality; predict join row counts for a small example with duplicate keys. | G17: Join checks and before/after row counts.
A18: 46301 | B18: DE | C18: Third normal form and relationships | D18: Remove a transitive dependency such as asset_id → unit_id → unit_name. | E18: Draw one-to-many and many-to-many relationships with optionality. | F18: Search third normal form transitive dependency ER diagram; explain an update anomaly and how the revised schema prevents it. | G18: A 3NF schema and relationship sketch.
... A68: 46326 | B68: DE | C68: Review through practice | D68: Run one existing mini-project from source to SQL result and explain the schema. | E68: Improve one awkward step. | F68: Search CSV to SQL normalized database pipeline walkthrough; narrate your own design, checks, rerun behavior, and reporting tradeoffs. | G68: A successful run, a normalization explanation, and one next improvement.

Sheet Progress
A2: October progress
A4: Days complete | B4: =COUNTIFS(G8:G38,"Complete") -> 5 | C4: of 31 days | D4: Minutes logged | E4: =SUM(F8:F38) -> 350
A5: Amber cells are editable. Select Done after P1 or its concept alternative; enter focused minutes for each area.
A6: A complete day requires Done and at least 25 minutes in BOTH areas. Optional P2 is not required. Note hands-on or concept in your output.
A7: Date | B7: DS status | C7: DS minutes | D7: DE status | E7: DE minutes | F7: Total minutes | G7: Daily minimum | H7: Output / learning / mode | I7: Uncertainty | J7: Next small step
A8: 46296 | B8: Done | C8: 60 | D8: Done | E8: 25 | F8: =IF(COUNT(C8,E8)=0,"",SUM(C8,E8)) -> 85 | G8: =IF(AND(B8="Done",D8="Done",C8>=25,E8>=25),"Complete","Pending") -> Complete | H8: Fail Mode 1: Using Age as a search criteria Fail Mode 2: Relying on Salary as some are missing Fail Mode 3: Performance Score
A9: 46297 | B9: Done | C9: 90 | D9: Done | E9: 25 | F9: =IF(COUNT(C9,E9)=0,"",SUM(C9,E9)) -> 115 | G9: =IF(AND(B9="Done",D9="Done",C9>=25,E9>=25),"Complete","Pending") -> Complete | H9: Both the DS and DE portion fell under eachother
A10: 46298 | B10: Done | C10: 25 | D10: Done | E10: 25 | F10: =IF(COUNT(C10,E10)=0,"",SUM(C10,E10)) -> 50 | G10: =IF(AND(B10="Done",D10="Done",C10>=25,E10>=25),"Complete","Pending") -> Complete | H10: Refernce day_3_to_5.md as I did a quiz over all this information | I10: Spend more time on candiate keys
A11: 46299 | B11: Done | C11: 25 | D11: Done | E11: 25 | F11: =IF(COUNT(C11,E11)=0,"",SUM(C11,E11)) -> 50 | G11: =IF(AND(B11="Done",D11="Done",C11>=25,E11>=25),"Complete","Pending") -> Complete | H11: Refernce day_3_to_5.md as I did a quiz over all this information | I11: Spend more time on candiate keys
A12: 46300 | B12: Done | C12: 25 | D12: Done | E12: 25 | F12: =IF(COUNT(C12,E12)=0,"",SUM(C12,E12)) -> 50 | G12: =IF(AND(B12="Done",D12="Done",C12>=25,E12>=25),"Complete","Pending") -> Complete | H12: Refernce day_3_to_5.md as I did a quiz over all this information | I12: Spend more time on candiate keys
A13: 46301 | B13: Not started | D13: Not started | F13: =IF(COUNT(C13,E13)=0,"",SUM(C13,E13)) | G13: =IF(AND(B13="Done",D13="Done",C13>=25,E13>=25),"Complete","Pending") -> Pending
A14: 46302 | B14: Not started | D14: Not started | F14: =IF(COUNT(C14,E14)=0,"",SUM(C14,E14)) | G14: =IF(AND(B14="Done",D14="Done",C14>=25,E14>=25),"Complete","Pending") -> Pending
A15: 46303 | B15: Not started | D15: Not started | F15: =IF(COUNT(C15,E15)=0,"",SUM(C15,E15)) | G15: =IF(AND(B15="Done",D15="Done",C15>=25,E15>=25),"Complete","Pending") -> Pending
A16: 46304 | B16: Not started | D16: Not started | F16: =IF(COUNT(C16,E16)=0,"",SUM(C16,E16)) | G16: =IF(AND(B16="Done",D16="Done",C16>=25,E16>=25),"Complete","Pending") -> Pending
A17: 46305 | B17: Not started | D17: Not started | F17: =IF(COUNT(C17,E17)=0,"",SUM(C17,E17)) | G17: =IF(AND(B17="Done",D17="Done",C17>=25,E17>=25),"Complete","Pending") -> Pending
A18: 46306 | B18: Not started | D18: Not started | F18: =IF(COUNT(C18,E18)=0,"",SUM(C18,E18)) | G18: =IF(AND(B18="Done",D18="Done",C18>=25,E18>=25),"Complete","Pending") -> Pending
A19: 46307 | B19: Not started | D19: Not started | F19: =IF(COUNT(C19,E19)=0,"",SUM(C19,E19)) | G19: =IF(AND(B19="Done",D19="Done",C19>=25,E19>=25),"Complete","Pending") -> Pending
A20: 46308 | B20: Not started | D20: Not started | F20: =IF(COUNT(C20,E20)=0,"",SUM(C20,E20)) | G20: =IF(AND(B20="Done",D20="Done",C20>=25,E20>=25),"Complete","Pending") -> Pending
A21: 46309 | B21: Not started | D21: Not started | F21: =IF(COUNT(C21,E21)=0,"",SUM(C21,E21)) | G21: =IF(AND(B21="Done",D21="Done",C21>=25,E21>=25),"Complete","Pending") -> Pending
A22: 46310 | B22: Not started | D22: Not started | F22: =IF(COUNT(C22,E22)=0,"",SUM(C22,E22)) | G22: =IF(AND(B22="Done",D22="Done",C22>=25,E22>=25),"Complete","Pending") -> Pending
A23: 46311 | B23: Not started | D23: Not started | F23: =IF(COUNT(C23,E23)=0,"",SUM(C23,E23)) | G23: =IF(AND(B23="Done",D23="Done",C23>=25,E23>=25),"Complete","Pending") -> Pending
A24: 46312 | B24: Not started | D24: Not started | F24: =IF(COUNT(C24,E24)=0,"",SUM(C24,E24)) | G24: =IF(AND(B24="Done",D24="Done",C24>=25,E24>=25),"Complete","Pending") -> Pending
... A38: 46326 | B38: Not started | D38: Not started | F38: =IF(COUNT(C38,E38)=0,"",SUM(C38,E38)) | G38: =IF(AND(B38="Done",D38="Done",C38>=25,E38>=25),"Complete","Pending") -> Pending

Sheet Guide
A2: How to use the plan
A5: Item | B5: Guidance
A6: Purpose | B6: A refresher for Sebastian, who already knows Python, pandas, SQL, visualization, and engineering fundamentals. Practice daily October 1–31; start the new job October 26.
A7: Minimum per area | B7: One 25-minute Pomodoro: 20 minutes on the core task and 5 minutes capturing the checkpoint. DS + DE = 50 focused minutes, about 55 with a break.
A8: Preferred per area | B8: 25 minutes P1, 5-minute break, 25 minutes P2, 5 minutes recording the result. About one hour per area, two hours total; split sessions across the day.
A9: Concept-only days | B9: Replace each hands-on track with its concept alternative. Spend 20 minutes listening, reading, or thinking and 5 recalling without the source. A voice note counts as output. For P2, work another example or critique a design.
A10: Search prompts | B10: Concept alternatives contain suggested YouTube/search topics, not researched video recommendations. Choose one relevant explanation; searching is not the task.
A11: Track progress | B11: In Progress, choose a status and enter focused minutes for each area. Done means the P1 task or concept alternative and a checkpoint are complete. A complete day also needs at least 25 minutes per area. Amber cells are editable.
A12: Record the result | B12: Log hands-on or concept mode, an output or voice-note location, something you can explain again, one uncertainty or failed check, and the next small step.
A13: Missed day | B13: Resume on the current date. Do not double the next day. If an earlier artifact is missing, use a tiny sample.
A14: October 26–31 | B14: Favor minimum mode around onboarding. Keep both tracks and the same mix of SQL, notebooks, APIs, visualization, databases, and pipelines. P2 remains optional; there is no capstone deadline.
A15: Recurring dataset | B15: Use 30–100 synthetic equipment-maintenance rows: assets, units, work orders, parts, and work-order parts. Include inconsistent IDs, duplicates, missing values, mixed dates, a semicolon-separated parts field, JSON metadata, and free-text notes.
A16: Data formats | B16: CSV is structured, though fields may be messy or semi-structured. Free-text maintenance notes supply the unstructured portion. Practice with all three.
... A33: Source | B33: Converted from Sebastian’s October 2026 Re-entry Plan, the Markdown plan created in this chat. Daily tasks, extensions, concept alternatives, and checkpoints are preserved.

Sheet Overview
A1: Technical Fluency Refresher — Project Dashboard
A3: Priority | B3: Technical fluency → stronger data science → analytics
A4: Start of project phase | B4: 46321
A5: Daily minimum | B5: 60 minutes; continue longer when in flow
A6: Projects | B6: 3
A7: Datasets | B7: User-selected; see Dataset Guide
A8: Warm-up history | B8: Original Daily plan / Progress / Guide sheets preserved
A10: Project | B10: Planned Window | C10: Goal | D10: Checklist Items | E10: Completed | F10: Progress
A11: Project 1 — Analytics & Dashboard | B11: Oct 26 – Nov 04, 2026 | C11: Build an end-to-end analytical workflow from a moderately messy dataset to defensible metrics, visuals, and a dashboard. | D11: =COUNTIF('Project Checklist'!$C$3:$C$146,A11) -> 40 | E11: =COUNTIFS('Project Checklist'!$C$3:$C$146,A11,'Project Checklist'!$H$3:$H$146,"Done") -> 30 | F11: =IFERROR(E11/D11,0) -> 0.75
A12: Project 2 — Data Science / ML | B12: Nov 05 – Nov 18, 2026 | C12: Practice the full data-science workflow: target definition, baselines, feature engineering, validation, diagnostics, interpretation, and uncertainty. | D12: =COUNTIF('Project Checklist'!$C$3:$C$146,A12) -> 56 | E12: =COUNTIFS('Project Checklist'!$C$3:$C$146,A12,'Project Checklist'!$H$3:$H$146,"Done") -> 0 | F12: =IFERROR(E12/D12,0) -> 0
A13: Project 3 — SQL + Integrated Workflow | B13: Nov 19 – Nov 30, 2026 | C13: Build a realistic source → staging → PostgreSQL → analytical output workflow, then use the stored data for analysis or a lightweight model. | D13: =COUNTIF('Project Checklist'!$C$3:$C$146,A13) -> 48 | E13: =COUNTIFS('Project Checklist'!$C$3:$C$146,A13,'Project Checklist'!$H$3:$H$146,"Done") -> 0 | F13: =IFERROR(E13/D13,0) -> 0
A16: KPI | B16: Value
A17: Total checklist items | B17: =COUNTA('Project Checklist'!F3:F146) -> 144
A18: Completed checklist items | B18: =COUNTIF('Project Checklist'!H3:H146,"Done") -> 30
A19: Total learning hours | B19: =SUM('Daily Journal'!L3:L38)/60 -> 3.5
A20: Days with logged time | B20: =COUNTIF('Daily Journal'!L3:L38,">0") -> 4
A23: How to use this workbook
A24: 1. | B24: Pick a dataset using Dataset Guide. Do not force a topic; choose data that creates useful questions.
A25: 2. | B25: Use Project Checklist as the planned work. The checklist is sequential, but you may continue beyond the day's minimum.
A26: 3. | B26: Record what actually happened in Daily Journal: concepts practiced, uncertainty, decision, time, and next step.
A27: 4. | B27: Use DS Concepts when a project step exposes a weak concept. The point is to research it because the project needs it.
A28: 5. | B28: Realism Questions are prompts. Answer them before looking for a solution whenever possible.
A29: 6. | B29: Project 3 intentionally introduces PostgreSQL/Docker only after pandas/DS fluency is re-established.

Sheet Project Checklist
A1: Project-Based Refresher Checklist
A2: Date | B2: Day | C2: Project | D2: Project Phase | E2: Daily Focus | F2: Checklist Item | G2: Category | H2: Status | I2: DS Concept(s) | J2: DE Concept(s) | K2: Realism Question | L2: Expected Output | M2: Stretch / If In Flow
A3: 46321 | B3: 1 | C3: Project 1 — Analytics & Dashboard | D3: Problem framing | E3: Choose and understand the dataset before cleaning it | F3: Confirm dataset fits the project-selection criteria | G3: Combined | H3: Done | I3: Observational unit/grain; measurement scales; problem framing | J3: Source inspection; ingestion assumptions; data contracts | K3: What would make one row ambiguous, and what would you need from the source owner to resolve it? | L3: Dataset fit note + grain statement + initial questions | M3: Create a short data dictionary for the most important fields.
A4: 46321 | B4: 1 | C4: Project 1 — Analytics & Dashboard | D4: Problem framing | E4: Choose and understand the dataset before cleaning it | F4: State what one row represents and identify the likely unit of analysis | G4: Data Science | H4: Done | I4: Observational unit/grain; measurement scales; problem framing | J4: Source inspection; ingestion assumptions; data contracts | K4: What would make one row ambiguous, and what would you need from the source owner to resolve it? | L4: Dataset fit note + grain statement + initial questions | M4: Create a short data dictionary for the most important fields.
A5: 46321 | B5: 1 | C5: Project 1 — Analytics & Dashboard | D5: Problem framing | E5: Choose and understand the dataset before cleaning it | F5: Write 3–5 analytical questions without touching the data yet | G5: Data Engineering | H5: Done | I5: Observational unit/grain; measurement scales; problem framing | J5: Source inspection; ingestion assumptions; data contracts | K5: What would make one row ambiguous, and what would you need from the source owner to resolve it? | L5: Dataset fit note + grain statement + initial questions | M5: Create a short data dictionary for the most important fields.
A6: 46321 | B6: 1 | C6: Project 1 — Analytics & Dashboard | D6: Problem framing | E6: Choose and understand the dataset before cleaning it | F6: List assumptions you are currently making about the source | G6: Review | H6: Done | I6: Observational unit/grain; measurement scales; problem framing | J6: Source inspection; ingestion assumptions; data contracts | K6: What would make one row ambiguous, and what would you need from the source owner to resolve it? | L6: Dataset fit note + grain statement + initial questions | M6: Create a short data dictionary for the most important fields.
A7: 46322 | B7: 2 | C7: Project 1 — Analytics & Dashboard | D7: Ingestion & profiling | E7: Load deliberately and build a trustworthy first profile | F7: Load with explicit encoding/delimiter where known | G7: Combined | H7: Done | I7: Descriptive statistics; missingness; distributions | J7: Encoding; delimiter; dtypes; identifiers; schema inspection | K7: Which columns would be most dangerous for pandas to infer incorrectly? | L7: Baseline profiling notebook | M7: Create an input contract with 3–5 rejection/warning rules.
A8: 46322 | B8: 2 | C8: Project 1 — Analytics & Dashboard | D8: Ingestion & profiling | E8: Load deliberately and build a trustworthy first profile | F8: Protect identifier-like fields from unwanted numeric coercion | G8: Data Science | H8: Done | I8: Descriptive statistics; missingness; distributions | J8: Encoding; delimiter; dtypes; identifiers; schema inspection | K8: Which columns would be most dangerous for pandas to infer incorrectly? | L8: Baseline profiling notebook | M8: Create an input contract with 3–5 rejection/warning rules.
A9: 46322 | B9: 2 | C9: Project 1 — Analytics & Dashboard | D9: Ingestion & profiling | E9: Load deliberately and build a trustworthy first profile | F9: Profile shape, dtypes, missingness, cardinality, and duplicates | G9: Data Engineering | H9: Done | I9: Descriptive statistics; missingness; distributions | J9: Encoding; delimiter; dtypes; identifiers; schema inspection | K9: Which columns would be most dangerous for pandas to infer incorrectly? | L9: Baseline profiling notebook | M9: Create an input contract with 3–5 rejection/warning rules.
A10: 46322 | B10: 2 | C10: Project 1 — Analytics & Dashboard | D10: Ingestion & profiling | E10: Load deliberately and build a trustworthy first profile | F10: Flag malformed or suspicious fields rather than fixing them immediately | G10: Review | H10: Done | I10: Descriptive statistics; missingness; distributions | J10: Encoding; delimiter; dtypes; identifiers; schema inspection | K10: Which columns would be most dangerous for pandas to infer incorrectly? | L10: Baseline profiling notebook | M10: Create an input contract with 3–5 rejection/warning rules.
A11: 46323 | B11: 3 | C11: Project 1 — Analytics & Dashboard | D11: Data quality investigation | E11: Decide which problems are errors, oddities, or valid edge cases | F11: Inspect missingness patterns, not only null totals | G11: Combined | H11: Done | I11: Missing-data mechanisms; outliers; categorical validity | J11: Validation rules; duplicate detection; rejected-row logic | K11: If a value looks impossible, what evidence would justify correcting it versus quarantining it? | L11: Data-quality findings with decisions | M11: Create a rejected/flagged rows dataframe with reasons.
A12: 46323 | B12: 3 | C12: Project 1 — Analytics & Dashboard | D12: Data quality investigation | E12: Decide which problems are errors, oddities, or valid edge cases | F12: Inspect categorical values for inconsistent labels | G12: Data Science | H12: Done | I12: Missing-data mechanisms; outliers; categorical validity | J12: Validation rules; duplicate detection; rejected-row logic | K12: If a value looks impossible, what evidence would justify correcting it versus quarantining it? | L12: Data-quality findings with decisions | M12: Create a rejected/flagged rows dataframe with reasons.
A13: 46323 | B13: 3 | C13: Project 1 — Analytics & Dashboard | D13: Data quality investigation | E13: Decide which problems are errors, oddities, or valid edge cases | F13: Inspect numeric ranges and extreme values | G13: Data Engineering | H13: Done | I13: Missing-data mechanisms; outliers; categorical validity | J13: Validation rules; duplicate detection; rejected-row logic | K13: If a value looks impossible, what evidence would justify correcting it versus quarantining it? | L13: Data-quality findings with decisions | M13: Create a rejected/flagged rows dataframe with reasons.
A14: 46323 | B14: 3 | C14: Project 1 — Analytics & Dashboard | D14: Data quality investigation | E14: Decide which problems are errors, oddities, or valid edge cases | F14: Investigate duplicate candidates using the established grain | G14: Review | H14: Skipped | I14: Missing-data mechanisms; outliers; categorical validity | J14: Validation rules; duplicate detection; rejected-row logic | K14: If a value looks impossible, what evidence would justify correcting it versus quarantining it? | L14: Data-quality findings with decisions | M14: Create a rejected/flagged rows dataframe with reasons.
... A146: 46356 | B146: 36 | C146: Project 3 — SQL + Integrated Workflow | D146: End-to-end review | E146: Run the whole workflow and explain it | F146: Record DS/DE weak spots and next learning priorities | G146: Review | H146: Not started | I146: Analytical communication; uncertainty; limitations | J146: Reproducibility; lineage; recovery | K146: Could another analyst rebuild the result from only your repository and source files? | L146: End-to-end run + final retrospective | M146: Give yourself a technical walkthrough covering both the data model and the analysis.

Sheet Daily Journal
A1: Daily Learning Journal
A2: Date | B2: Project | C2: Project Phase | D2: Daily Focus | E2: Checklist Completion | F2: DS Concepts Practiced | G2: DE Concepts Practiced | H2: What I Learned | I2: Problem / Uncertainty | J2: Decision Made | K2: Next Step | L2: Time Spent (Minutes) | M2: Artifact / Notebook
A3: 46321 | B3: Project 1 — Analytics & Dashboard | C3: Problem framing | D3: Choose and understand the dataset before cleaning it | E3: =IFERROR(COUNTIFS('Project Checklist'!$A$3:$A$146,A3,'Project Checklist'!$H$3:$H$146,"Done")/COUNTIF('Project Checklist'!$A$3:$A$146,A3),0) -> 1 | F3: First step, find an interesting dataset, that dataset being a test taking dataset (Data exploration) | G3: Thinking about ingestion and overall how the data is going to move | L3: 120 | M3: data_explore.ipynb
A4: 46322 | B4: Project 1 — Analytics & Dashboard | C4: Ingestion & profiling | D4: Load deliberately and build a trustworthy first profile | E4: =IFERROR(COUNTIFS('Project Checklist'!$A$3:$A$146,A4,'Project Checklist'!$H$3:$H$146,"Done")/COUNTIF('Project Checklist'!$A$3:$A$146,A4),0) -> 1 | F4: Import data set as raw_spf_df using pandas data_profiling tool | L4: 30 | M4: data_explore.ipynb
A5: 46323 | B5: Project 1 — Analytics & Dashboard | C5: Data quality investigation | D5: Decide which problems are errors, oddities, or valid edge cases | E5: =IFERROR(COUNTIFS('Project Checklist'!$A$3:$A$146,A5,'Project Checklist'!$H$3:$H$146,"Done")/COUNTIF('Project Checklist'!$A$3:$A$146,A5),0) -> 0.75 | F5: Look at anomlies within the dataset | G5: Use python fuction to make this process easier | H5: Ordinal and nominal categories. | L5: 30 | M5: data_explore.ipynb
A6: 46324 | B6: Project 1 — Analytics & Dashboard | C6: Cleaning & validation | D6: Create a defensible silver/clean dataset | E6: =IFERROR(COUNTIFS('Project Checklist'!$A$3:$A$146,A6,'Project Checklist'!$H$3:$H$146,"Done")/COUNTIF('Project Checklist'!$A$3:$A$146,A6),0) -> 1 | H6: Grain became much clearer when I related it to organizational levels such as wing, squadron, flight, and individual records. I also reinforced that cleaning should be based on the analytical purpose rather than making changes simply because a cleaning technique exists. I removed 293 records whose missing information prevented them from contributing meaningfully to the planned analysis and otherwise preserved the dataset because it was already relatively clean. | L6: 30
A7: 46325 | B7: Project 1 — Analytics & Dashboard | C7: Descriptive analysis | D7: Move from clean data to meaningful summaries | E7: =IFERROR(COUNTIFS('Project Checklist'!$A$3:$A$146,A7,'Project Checklist'!$H$3:$H$146,"Done")/COUNTIF('Project Checklist'!$A$3:$A$146,A7),0) -> 1 | F7: Working with establishing the numerator, denominator, and metric as well as the exclusion | H7: Numerator = total students Denominator = number of classrooms Metric = average students per classroom
A8: 46326 | B8: Project 1 — Analytics & Dashboard | C8: Relationships & statistical thinking | D8: Investigate relationships without overclaiming | E8: =IFERROR(COUNTIFS('Project Checklist'!$A$3:$A$146,A8,'Project Checklist'!$H$3:$H$146,"Done")/COUNTIF('Project Checklist'!$A$3:$A$146,A8),0) -> 1 | F8: Begin understanding the relationships between exam and both our numeric and categorical values.
A9: 46327 | B9: Project 1 — Analytics & Dashboard | C9: Visualization design | D9: Choose visuals that answer questions rather than decorate | E9: =IFERROR(COUNTIFS('Project Checklist'!$A$3:$A$146,A9,'Project Checklist'!$H$3:$H$146,"Done")/COUNTIF('Project Checklist'!$A$3:$A$146,A9),0) -> 0.75 | F9: Continue to work throught the visuals as we create the report.
A10: 46328 | B10: Project 1 — Analytics & Dashboard | C10: Dashboard build | D10: Assemble a first dashboard from validated metrics | E10: =IFERROR(COUNTIFS('Project Checklist'!$A$3:$A$146,A10,'Project Checklist'!$H$3:$H$146,"Done")/COUNTIF('Project Checklist'!$A$3:$A$146,A10),0) -> 1 | F10: Planning to create a report and try to create a product that is focused in creating a productive outcome
A11: 46329 | B11: Project 1 — Analytics & Dashboard | C11: Robustness & refinement | D11: Stress-test conclusions and dashboard logic | E11: =IFERROR(COUNTIFS('Project Checklist'!$A$3:$A$146,A11,'Project Checklist'!$H$3:$H$146,"Done")/COUNTIF('Project Checklist'!$A$3:$A$146,A11),0) -> 0
A12: 46330 | B12: Project 1 — Analytics & Dashboard | C12: Communicate & review | D12: Explain the project end to end and identify weak spots | E12: =IFERROR(COUNTIFS('Project Checklist'!$A$3:$A$146,A12,'Project Checklist'!$H$3:$H$146,"Done")/COUNTIF('Project Checklist'!$A$3:$A$146,A12),0) -> 0
A13: 46331 | B13: Project 2 — Data Science / ML | C13: Problem & target | D13: Define a prediction problem worth modeling | E13: =IFERROR(COUNTIFS('Project Checklist'!$A$3:$A$146,A13,'Project Checklist'!$H$3:$H$146,"Done")/COUNTIF('Project Checklist'!$A$3:$A$146,A13),0) -> 0
A14: 46332 | B14: Project 2 — Data Science / ML | C14: Split strategy | D14: Design evaluation before feature engineering | E14: =IFERROR(COUNTIFS('Project Checklist'!$A$3:$A$146,A14,'Project Checklist'!$H$3:$H$146,"Done")/COUNTIF('Project Checklist'!$A$3:$A$146,A14),0) -> 0
A15: 46333 | B15: Project 2 — Data Science / ML | C15: Baseline | D15: Create something simple that every later model must beat | E15: =IFERROR(COUNTIFS('Project Checklist'!$A$3:$A$146,A15,'Project Checklist'!$H$3:$H$146,"Done")/COUNTIF('Project Checklist'!$A$3:$A$146,A15),0) -> 0
A16: 46334 | B16: Project 2 — Data Science / ML | C16: Preprocessing | D16: Build preprocessing without leaking information | E16: =IFERROR(COUNTIFS('Project Checklist'!$A$3:$A$146,A16,'Project Checklist'!$H$3:$H$146,"Done")/COUNTIF('Project Checklist'!$A$3:$A$146,A16),0) -> 0
A17: 46335 | B17: Project 2 — Data Science / ML | C17: Feature engineering | D17: Create features from domain logic, not noise | E17: =IFERROR(COUNTIFS('Project Checklist'!$A$3:$A$146,A17,'Project Checklist'!$H$3:$H$146,"Done")/COUNTIF('Project Checklist'!$A$3:$A$146,A17),0) -> 0
A18: 46336 | B18: Project 2 — Data Science / ML | C18: First models | D18: Train a small, interpretable model set | E18: =IFERROR(COUNTIFS('Project Checklist'!$A$3:$A$146,A18,'Project Checklist'!$H$3:$H$146,"Done")/COUNTIF('Project Checklist'!$A$3:$A$146,A18),0) -> 0
A19: 46337 | B19: Project 2 — Data Science / ML | C19: Evaluation depth | D19: Understand what the headline metric hides | E19: =IFERROR(COUNTIFS('Project Checklist'!$A$3:$A$146,A19,'Project Checklist'!$H$3:$H$146,"Done")/COUNTIF('Project Checklist'!$A$3:$A$146,A19),0) -> 0
A20: 46338 | B20: Project 2 — Data Science / ML | C20: Cross-validation | D20: Estimate model stability | E20: =IFERROR(COUNTIFS('Project Checklist'!$A$3:$A$146,A20,'Project Checklist'!$H$3:$H$146,"Done")/COUNTIF('Project Checklist'!$A$3:$A$146,A20),0) -> 0
A21: 46339 | B21: Project 2 — Data Science / ML | C21: Tuning | D21: Tune deliberately rather than exhaustively | E21: =IFERROR(COUNTIFS('Project Checklist'!$A$3:$A$146,A21,'Project Checklist'!$H$3:$H$146,"Done")/COUNTIF('Project Checklist'!$A$3:$A$146,A21),0) -> 0
A22: 46340 | B22: Project 2 — Data Science / ML | C22: Diagnostics | D22: Find where the model fails | E22: =IFERROR(COUNTIFS('Project Checklist'!$A$3:$A$146,A22,'Project Checklist'!$H$3:$H$146,"Done")/COUNTIF('Project Checklist'!$A$3:$A$146,A22),0) -> 0
... A38: 46356 | B38: Project 3 — SQL + Integrated Workflow | C38: End-to-end review | D38: Run the whole workflow and explain it | E38: =IFERROR(COUNTIFS('Project Checklist'!$A$3:$A$146,A38,'Project Checklist'!$H$3:$H$146,"Done")/COUNTIF('Project Checklist'!$A$3:$A$146,A38),0) -> 0

Sheet DS Concepts
A1: Data Science Concepts to Keep in Mind
A2: Concept | B2: Plain-English Meaning | C2: Questions to Ask Yourself | D2: When It Matters | E2: Project Tie-In | F2: Quick Practice
A3: Problem framing | B3: Translate a vague goal into a measurable analytical or predictive question. | C3: What decision is this meant to support? What exactly is the outcome? | D3: Before analysis or modeling | E3: All projects | F3: Rewrite one vague question into a measurable one.
A4: Observational unit / grain | B4: Define what one row or one prediction represents. | C4: What does one row mean before and after this transformation? | D4: Always | E4: All projects | F4: State the grain before and after a groupby, join, or explode.
A5: Measurement scales | B5: Know whether a variable is nominal, ordinal, interval, or ratio-like. | C5: Does averaging this field make sense? Does order matter? | D5: Profiling and feature design | E5: Projects 1–2 | F5: Classify five columns and justify the operations you would allow.
A6: Descriptive statistics | B6: Summarize center, spread, shape, and count. | C6: Should I use mean or median? What does spread add? | D6: EDA | E6: Project 1 | F6: Compare mean, median, IQR, and standard deviation for one variable.
A7: Distributions | B7: Understand how values are shaped, skewed, or clustered. | C7: Is the distribution symmetric? Heavy-tailed? Multimodal? | D7: EDA and modeling | E7: Projects 1–2 | F7: Plot a histogram and ECDF; explain what each reveals.
A8: Sampling & representativeness | B8: Determine whether the observed data represents the population of interest. | C8: Who is missing from the data? How was this sample created? | D8: Any inference | E8: Projects 1–2 | F8: Write two ways the sample could be biased.
A9: Missing data | B9: Missingness can carry information and can bias results. | C9: Is missingness random, systematic, or tied to another variable? | D9: Cleaning and modeling | E9: Projects 1–2 | F9: Compare missingness rates across two subgroups.
A10: Outliers | B10: Extreme values can be errors, valid rare cases, or the most important observations. | C10: What evidence says this value is wrong? | D10: Cleaning and diagnostics | E10: Projects 1–2 | F10: Show a metric with and without an extreme value.
A11: Correlation vs causation | B11: Association does not establish cause. | C11: What confounder could explain this relationship? | D11: Relationship analysis | E11: Project 1 | F11: Write one causal-sounding sentence, then make it appropriately non-causal.
A12: Confounding | B12: A third variable can create or hide an apparent relationship. | C12: What variable influences both X and Y? | D12: EDA and interpretation | E12: Projects 1–2 | F12: Stratify one relationship by a plausible confounder.
A13: Hypothesis testing | B13: Quantify how surprising data would be under a null assumption. | C13: What is H0? Are assumptions met? Is this test even needed? | D13: Comparisons | E13: Projects 1–2 | F13: State H0/H1 and assumptions before running a test.
... A31: Communicating limitations | B31: State what the analysis/model does not establish. | C31: What would I warn someone not to conclude? | D31: Final reporting | E31: All projects | F31: Write three limitations in stakeholder language.

Sheet Dataset Guide
A1: Dataset Selection Guide
A2: Criterion | B2: Project 1 — Analytics/Dashboard | C2: Project 2 — ML | D2: Project 3 — SQL/Integrated | E2: Why
A3: Rows | B3: ~10k–100k | C3: Prefer ~20k+ if possible; enough positive/negative or outcome examples | D3: ~25k+ or multiple files/batches; size should justify persistence | E3: Large enough to expose real workflow issues, small enough to iterate quickly.
A4: Columns | B4: ~10–30 | C4: ~10–50 useful raw features | D4: Multiple related fields/files or wide denormalized source | E4: Enough complexity without spending the project decoding hundreds of columns.
A5: Messiness | B5: Medium | C5: Medium; imperfect but recoverable | D5: Medium/high; schema and updates should matter | E5: You want real decisions, not a perfectly curated tutorial file.
A6: Data types | B6: Numeric + categorical + dates + IDs | C6: Mixed predictors + clear target | D6: IDs + dates/timestamps + categories + measures | E6: Mixed types force realistic profiling and preprocessing.
A7: Missing values | B7: Some, with patterns worth investigating | C7: Some; avoid datasets where everything is already imputed | D7: Some plus rules for accepted/rejected rows | E7: Missingness creates analytical and engineering decisions.
A8: Categorical quality | B8: Some inconsistent labels are useful | C8: Categories that require encoding or consolidation | D8: Repeated categories/entities that can become dimensions/tables | E8: Good practice for standardization and modeling.
A9: Dates / time | B9: Prefer at least one date/time field | C9: Strongly preferred if prediction horizon matters | D9: Strongly preferred for incremental loads | E9: Time enables realistic splits, trends, and update logic.
A10: Identifiers | B10: At least one ID-like field | C10: Useful for grouping and leakage checks | D10: Important; multiple keys/relationships preferred | E10: Identifiers force grain/key reasoning.
A11: Denormalization | B11: Nice to have | C11: Optional | D11: Strongly preferred | E11: Project 3 should create a reason to model data relationally.
A12: Business questions | B12: At least 3 plausible questions | C12: One clear predictive target plus exploratory questions | D12: Several SQL/analytical outputs | E12: The dataset should support iteration rather than one obvious chart.
A13: Target variable | B13: Not required | C13: Required or reasonably derivable | D13: Optional | E13: ML needs a well-defined outcome.
... A15: Safety | B15: Public/synthetic/non-sensitive | C15: Public/synthetic/non-sensitive | D15: Public/synthetic/non-sensitive | E15: Do not use classified, controlled, employer, or personal data in personal practice.

Sheet New Workflow Guide
A1: How the New Refresher Works
A3: Principle | B3: Guidance
A4: Why the old plan changed | B4: The first five completed days served their purpose: rebuilding learning discipline after vacation. The project phase now replaces isolated DS/DE daily exercises.
A5: Core model | B5: Projects drive the learning. Data engineering and data science are combined in the same workflow rather than treated as two unrelated tracks.
A6: Daily minimum | B6: Plan for at least 60 focused minutes. There is no upper limit; continue when you are in flow.
A7: Daily checklist | B7: Use Project Checklist to see the next concrete actions. Mark each item Not started, In progress, Done, Blocked, or Skipped.
A8: Daily journal | B8: Use Daily Journal once per day to record DS/DE concepts practiced, what you learned, uncertainty, decisions, next step, time, and artifact location.
A9: Data science emphasis | B9: When the project reaches a concept you are weak on, use DS Concepts as a research menu. Learn the concept because the project creates a reason for it.
A10: Realism questions | B10: Treat the realism prompt as a short quiz. Answer it before looking for help whenever possible.
A11: Project 1 | B11: Analytics/dashboard workflow: source understanding → profiling → cleaning → statistics → visualization → dashboard → robustness → communication.
A12: Project 2 | B12: ML workflow: target → split → baseline → preprocessing → features → modeling → evaluation → diagnostics → interpretation → uncertainty.
A13: Project 3 | B13: Integrated workflow: Docker/PostgreSQL → staging → relational model → constraints → SQL → analytical layer → updates → data quality → end-to-end rerun.
A14: SQL timing | B14: Do not move to PostgreSQL because 'data engineers use databases.' Move when persistence, relationships, repeated loads, constraints, or SQL querying justify it.
... A17: Existing sheets | B17: The original Daily plan, Progress, and Guide remain in the workbook as the warm-up/history from the first phase.
